strip_notebook_output/__init__.py
strip_notebook_output/strip_output.py
tests/__init__.py
strip_notebook_output-0.0.3.dist-info/LICENSE-APACHE
strip_notebook_output-0.0.3.dist-info/LICENSE-MIT
strip_notebook_output-0.0.3.dist-info/METADATA
strip_notebook_output-0.0.3.dist-info/WHEEL
strip_notebook_output-0.0.3.dist-info/top_level.txt
strip_notebook_output-0.0.3.dist-info/RECORD
